import_db/__init__.py
import_db/__main__.py
import_db/server.py
import_db-0.0.726.dist-info/METADATA
import_db-0.0.726.dist-info/WHEEL
import_db-0.0.726.dist-info/top_level.txt
import_db-0.0.726.dist-info/RECORD
