Metadata-Version: 2.1
Name: import-db
Version: 0.0.726
Summary: Hack the Box Team Support Services
Requires-Dist: pymetasploit3
Requires-Dist: flask
Provides-Extra: rel
Requires-Dist: twine ; extra == 'rel'
Provides-Extra: test
Requires-Dist: coverage ; extra == 'test'
Requires-Dist: pytest ; extra == 'test'
